[{"insert":"🢂","attributes":{"background":"#303030","color":"#b0b0b0"}},{"insert":" ","attributes":{"bold":true}},{"insert":"Download","attributes":{"color":"#ffffff","bold":true}},{"insert":" a single file from the s3 bucket using this API.","attributes":{"color":"#ffffff"}},{"insert":"\n\n\n","attributes":{"header":5}},{"insert":"Input : Provide the below key in "},{"insert":"JSON format ","attributes":{"bold":true}},{"insert":":"},{"insert":"\n","attributes":{"header":5}},{"insert":"Key","attributes":{"bold":true}},{"insert":"\n","attributes":{"table":"row-ipqw"}},{"insert":"Value","attributes":{"bold":true}},{"insert":"\n","attributes":{"table":"row-ipqw"}},{"insert":"bucketName","attributes":{"bold":true}},{"insert":"\n","attributes":{"table":"row-jh9a"}},{"insert":"YOUR_S3_BUCKETNAME","attributes":{"bold":true}},{"insert":"\n","attributes":{"table":"row-jh9a"}},{"insert":"targetFileWithPath","attributes":{"bold":true}},{"insert":"\n","attributes":{"table":"row-hty3"}},{"insert":"PROVIDE_FILESNAME_YOU_WANT_TO_DOWNLOAD","attributes":{"bold":true}},{"insert":"\n","attributes":{"table":"row-hty3"}},{"insert":"overrideFileName","attributes":{"bold":true}},{"insert":"\n","attributes":{"table":"row-zlk5"}},{"insert":"PROVIDE_FILENAME_YOU_WANT_TO_OVERRIDE","attributes":{"bold":true}},{"insert":"\n","attributes":{"table":"row-zlk5"}},{"insert":"\nRequest body Json example : "},{"insert":"\n","attributes":{"code-block":"plain"}},{"insert":"{"},{"insert":"\n","attributes":{"code-block":"plain"}},{"insert":"     \"bucketName\": \"my-document-bucket\","},{"insert":"\n","attributes":{"code-block":"plain"}},{"insert":"\t \"targetFileWithPath\": \"usr/document/hello.txt\","},{"insert":"\n","attributes":{"code-block":"plain"}},{"insert":"     \"overrideFileName\": \"FTPDownloadedFile.txt\""},{"insert":"\n","attributes":{"code-block":"plain"}},{"insert":"}"},{"insert":"\n","attributes":{"code-block":"plain"}},{"insert":"\n\n"},{"insert":"Output : Download the file provided.","attributes":{"color":"#66b966"}},{"insert":"\n","attributes":{"header":5}},{"insert":"\n\n"},{"insert":"API Working Mechanism : ","attributes":{"color":"#66a3e0"}},{"insert":"\n","attributes":{"header":6}},{"insert":"User : Provide remote directory file name with actual path & override filename if you want to override file name."},{"insert":"\n","attributes":{"header":6}},{"insert":"Api : call to utility class for connecting with the FTP client, utility class got all the secret then try to connect with respected server, after connected download file from server."},{"insert":"\n","attributes":{"header":6}},{"insert":"\nNote: Set region, accessKeyId & secretAccessKeyin API Maker secret management."},{"insert":"\n","attributes":{"code-block":"plain"}},{"insert":"\n"}]